cdk_s3_bucketreplication/__init__.py
cdk_s3_bucketreplication/py.typed
cdk_s3_bucketreplication/_jsii/__init__.py
cdk_s3_bucketreplication/_jsii/cdk-s3-bucketreplication@0.0.20.jsii.tgz
cdk_s3_bucketreplication-0.0.20.dist-info/LICENSE
cdk_s3_bucketreplication-0.0.20.dist-info/METADATA
cdk_s3_bucketreplication-0.0.20.dist-info/WHEEL
cdk_s3_bucketreplication-0.0.20.dist-info/top_level.txt
cdk_s3_bucketreplication-0.0.20.dist-info/RECORD
