Metadata-Version: 2.1
Name: cdk-s3-bucketreplication
Version: 0.0.20
Summary: cdk-s3-bucketreplication
Home-page: https://github.com/rogerchi/cdk-s3-bucketreplication.git
Author: Roger Chi<roger@rogerchi.com>
License: Apache-2.0
Project-URL: Source, https://github.com/rogerchi/cdk-s3-bucketreplication.git
Classifier: Intended Audience :: Developers
Classifier: Operating System :: OS Independent
Classifier: Programming Language :: JavaScript
Classifier: Programming Language :: Python :: 3 :: Only
Classifier: Programming Language :: Python :: 3.7
Classifier: Programming Language :: Python :: 3.8
Classifier: Programming Language :: Python :: 3.9
Classifier: Programming Language :: Python :: 3.10
Classifier: Typing :: Typed
Classifier: Development Status :: 5 - Production/Stable
Classifier: License :: OSI Approved
Requires-Python: ~=3.7
License-File: LICENSE
Requires-Dist: aws-cdk.aws-iam (<2.0.0,>=1.147.0)
Requires-Dist: aws-cdk.aws-s3 (<2.0.0,>=1.147.0)
Requires-Dist: aws-cdk.core (<2.0.0,>=1.147.0)
Requires-Dist: constructs (<4.0.0,>=3.2.27)
Requires-Dist: jsii (<2.0.0,>=1.70.0)
Requires-Dist: publication (>=0.0.3)
Requires-Dist: typeguard (~=2.13.3)
